messagebird/__init__.py
messagebird/balance.py
messagebird/base.py
messagebird/base_list.py
messagebird/call.py
messagebird/call_data.py
messagebird/call_flow.py
messagebird/call_list.py
messagebird/client.py
messagebird/contact.py
messagebird/conversation.py
messagebird/conversation_channel.py
messagebird/conversation_contact.py
messagebird/conversation_message.py
messagebird/conversation_webhook.py
messagebird/error.py
messagebird/formats.py
messagebird/group.py
messagebird/hlr.py
messagebird/http_client.py
messagebird/lookup.py
messagebird/message.py
messagebird/mms.py
messagebird/number.py
messagebird/recipient.py
messagebird/request_validator.py
messagebird/serde.py
messagebird/signed_request.py
messagebird/validation.py
messagebird/verify.py
messagebird/version.py
messagebird/voice_recording.py
messagebird/voice_transcription.py
messagebird/voice_transcription_data.py
messagebird/voice_webhook.py
messagebird/voicemessage.py
messagebird/webhook.py
messagebird-2.1.0.dist-info/LICENSE
messagebird-2.1.0.dist-info/METADATA
messagebird-2.1.0.dist-info/WHEEL
messagebird-2.1.0.dist-info/top_level.txt
messagebird-2.1.0.dist-info/RECORD
