Metadata-Version: 2.1
Name: messagebird
Version: 2.1.0
Summary: MessageBird's REST API
Home-page: https://github.com/messagebird/python-rest-api
Author: MessageBird
Author-email: support@messagebird.com
License: BSD-2-Clause
Keywords: messagebird,sms
Platform: UNKNOWN
Classifier: Programming Language :: Python :: 3
Classifier: Programming Language :: Python :: 3.6
Classifier: Programming Language :: Python :: 3.7
Classifier: Programming Language :: Python :: 3.8
Classifier: Programming Language :: Python :: 3.9
Classifier: Operating System :: OS Independent
Provides-Extra: dev
License-File: LICENSE
